ChatRoom/Launcher.cp311-win_amd64.pyd
ChatRoom/_.py
ChatRoom/__init__.py
ChatRoom/compile
ChatRoom/encrypt.cp311-win_amd64.pyd
ChatRoom/gui.cp311-win_amd64.pyd
ChatRoom/gui_config.cp311-win_amd64.pyd
ChatRoom/log.cp311-win_amd64.pyd
ChatRoom/main.cp311-win_amd64.pyd
ChatRoom/net.cp311-win_amd64.pyd
ChatRoom/package.cp311-win_amd64.pyd
ChatRoom/sysinfo.cp311-win_amd64.pyd
ChatRoom/tools.cp311-win_amd64.pyd
ChatRoom/config/DefaultLogConfig.py
ChatRoom/config/Permission.py
ChatRoom/config/Theme.py
ChatRoom/data/FileNotFound
ChatRoom/data/FileNotSafePath
ChatRoom/data/Resource
ChatRoom/data/Package/DemoUser/demo/.FileIgnore
ChatRoom/data/Package/DemoUser/demo/__init__.py
ChatRoom/data/Package/DemoUser/demo/check.py
ChatRoom/data/Package/DemoUser/demo/client.py
ChatRoom/data/Package/DemoUser/demo/config.py
ChatRoom/data/Package/DemoUser/demo/log.py
ChatRoom/data/Package/DemoUser/demo/permission.py
ChatRoom/data/Package/DemoUser/demo/redeme.md
ChatRoom/data/Package/DemoUser/demo/server.py
ChatRoom/data/Package/DemoUser/demo/Lib/ext_lib.cp310-win_amd64.pyd
ChatRoom/data/Package/DemoUser/demo/data/TestDownloadFile
ChatRoom/data/Package/DemoUser/demo/data/config.json
ChatRoom/data/Package/DemoUser/demo/data/info.txt
ChatRoom/data/Package/DemoUser/demo2/__init__.py
ChatRoom/data/Package/DemoUser/demo2/client.py
ChatRoom/data/Package/DemoUser/demo2/config.py
ChatRoom/data/Package/DemoUser/demo2/ext_lib.py
ChatRoom/data/Package/DemoUser/demo2/log.py
ChatRoom/data/Package/DemoUser/demo2/permission.py
ChatRoom/data/Package/DemoUser/demo2/redeme.md
ChatRoom/data/Package/DemoUser/demo2/server.py
ChatRoom/data/Package/DemoUser/demo2/data/TestDownloadFile
ChatRoom/data/Package/DemoUser/demo2/data/config.json
ChatRoom/data/Package/DemoUser/demo2/data/info.txt
chatroom_jianjun-3.3.2.dist-info/METADATA
chatroom_jianjun-3.3.2.dist-info/WHEEL
chatroom_jianjun-3.3.2.dist-info/entry_points.txt
chatroom_jianjun-3.3.2.dist-info/top_level.txt
chatroom_jianjun-3.3.2.dist-info/RECORD
