Metadata-Version: 2.4
Name: ChatRoom-jianjun
Version: 3.3.2
Summary: Connecting python's !
Home-page: https://github.com/EVA-JianJun/ChatRoom-V3
Author: jianjun
Author-email: 910667956@qq.com
Requires-Dist: cprint-jianjun>=1.6.0
Requires-Dist: pycryptodome>=3.15.0
Requires-Dist: bcrypt>=3.2.0
Requires-Dist: psutil>=5.7.0
Requires-Dist: numpy>=1.23.3
Requires-Dist: pywin32>=306
Requires-Dist: pynput>=1.7.6
Requires-Dist: rich>=13.4.2
Requires-Dist: opencv-python>=4.7.0.72
Requires-Dist: ttkbootstrap>=1.9.0
Requires-Dist: yagmail>=0.15.280
Requires-Dist: pyperclip>=1.8.2
Requires-Dist: celldict>=2.0.1
Requires-Dist: ntplib>=0.4.0
Requires-Dist: PyLibreHardwareMonitor>=1.2.2
Requires-Dist: cloudpickle>=3.0.0
Requires-Dist: dill>=0.3.8
Requires-Dist: pygments>=2.17.2
Requires-Dist: pystray>=0.19.5
Requires-Dist: pillow
Dynamic: author
Dynamic: author-email
Dynamic: description
Dynamic: description-content-type
Dynamic: home-page
Dynamic: requires-dist
Dynamic: summary
